qsteed/VERSION.txt
qsteed/__init__.py
qsteed/first_build_db.py
qsteed/qsteed_config.py
qsteed/version.py
qsteed/apis/__init__.py
qsteed/apis/compiler_api.py
qsteed/apis/resourceDB_api.py
qsteed/backends/__init__.py
qsteed/backends/backend.py
qsteed/backends/chipinfo.py
qsteed/compiler/__init__.py
qsteed/compiler/compiler.py
qsteed/compiler/program_verification.py
qsteed/compiler/qasm_parser.py
qsteed/compiler/standardized_circuit.py
qsteed/config/__init__.py
qsteed/config/config.ini
qsteed/config/config_to_dict.py
qsteed/config/get_config.py
qsteed/dag/__init__.py
qsteed/dag/circuit_dag_convert.py
qsteed/dag/dagcircuit.py
qsteed/dag/instruction_node.py
qsteed/graph/__init__.py
qsteed/graph/circuitgraph.py
qsteed/graph/couplinggraph.py
qsteed/graph/graphkernel.py
qsteed/graph/graphmapping.py
qsteed/graph/similar_substructure.py
qsteed/parallelmanager/__init__.py
qsteed/parallelmanager/parallel_circuits.py
qsteed/passes/__init__.py
qsteed/passes/basepass.py
qsteed/passes/datadict.py
qsteed/passes/model.py
qsteed/passes/ParameterTuning/__init__.py
qsteed/passes/ParameterTuning/parametersubstitution.py
qsteed/passes/decomposition/CSD_decompose.py
qsteed/passes/decomposition/KAK_decompose.py
qsteed/passes/decomposition/ZYZ_decompose.py
qsteed/passes/decomposition/__init__.py
qsteed/passes/decomposition/one_qubit_decompose.py
qsteed/passes/decomposition/unitary_decompose.py
qsteed/passes/decomposition/utils/__init__.py
qsteed/passes/decomposition/utils/convert_utils.py
qsteed/passes/decomposition/utils/decompose_utils.py
qsteed/passes/decomposition/utils/matrix_utils.py
qsteed/passes/mapping/__init__.py
qsteed/passes/mapping/baselayout.py
qsteed/passes/mapping/layout/__init__.py
qsteed/passes/mapping/layout/sabre_layout.py
qsteed/passes/mapping/layout/sabre_layout_parallel.py
qsteed/passes/mapping/routing/__init__.py
qsteed/passes/mapping/routing/sabre_routing.py
qsteed/passes/optimization/__init__.py
qsteed/passes/optimization/one_qubit_optimization.py
qsteed-0.2.2.dist-info/LICENSE
qsteed-0.2.2.dist-info/METADATA
qsteed-0.2.2.dist-info/WHEEL
qsteed-0.2.2.dist-info/entry_points.txt
qsteed-0.2.2.dist-info/top_level.txt
qsteed-0.2.2.dist-info/RECORD
