Metadata-Version: 2.1
Name: qsteed
Version: 0.2.2
Summary: Quantum Software of Compilation for supporting Real Quantum device
Home-page: https://github.com/BAQIS-Quantum/QSteed
Author: Xuhongze
Author-email: Xuhongze <xhzby1995@163.com>
License: Apache-2.0 License
Project-URL: Homepage, https://github.com/BAQIS-Quantum/QSteed
Project-URL: Documentation, https://github.com/BAQIS-Quantum/QSteed/wiki
Project-URL: Source, https://github.com/BAQIS-Quantum/QSteed
Project-URL: Issues, https://github.com/BAQIS-Quantum/QSteed/issues
Keywords: qsteed,quantum compiling,quantum computing,quantum operating system
Requires-Python: >=3.10
License-File: LICENSE
Requires-Dist: dill >=0.3.8
Requires-Dist: ipython >=8.14.0
Requires-Dist: matplotlib >=3.5.2
Requires-Dist: networkx >=2.6.3
Requires-Dist: numpy <2.0.0,>=1.20.3
Requires-Dist: Pillow >=10.4.0
Requires-Dist: graphviz >=0.14.2
Requires-Dist: rich >=13.7.1
Requires-Dist: scipy >=1.8.1
Requires-Dist: tabulate >=0.9.0
Requires-Dist: sqlalchemy >=2.0.28
Requires-Dist: flask >=3.0.2
Requires-Dist: pymysql >=1.1.0
Requires-Dist: flask-sqlalchemy >=3.1.1
Provides-Extra: tests
Requires-Dist: pytest ; extra == 'tests'
